eazyml_xai_image/__init__.py
eazyml_xai_image/Darwin_arm64/__init__.py
eazyml_xai_image/Darwin_arm64/eazyml_xai_image/__init__.cpython-310-darwin.so
eazyml_xai_image/Darwin_arm64/eazyml_xai_image/__init__.cpython-311-darwin.so
eazyml_xai_image/Darwin_arm64/eazyml_xai_image/__init__.cpython-312-darwin.so
eazyml_xai_image/Darwin_arm64/eazyml_xai_image/__init__.cpython-38-darwin.so
eazyml_xai_image/Darwin_arm64/eazyml_xai_image/__init__.cpython-39-darwin.so
eazyml_xai_image/Darwin_arm64/eazyml_xai_image/client.cpython-310-darwin.so
eazyml_xai_image/Darwin_arm64/eazyml_xai_image/client.cpython-311-darwin.so
eazyml_xai_image/Darwin_arm64/eazyml_xai_image/client.cpython-312-darwin.so
eazyml_xai_image/Darwin_arm64/eazyml_xai_image/client.cpython-38-darwin.so
eazyml_xai_image/Darwin_arm64/eazyml_xai_image/client.cpython-39-darwin.so
eazyml_xai_image/Darwin_arm64/eazyml_xai_image/globals/__init__.cpython-310-darwin.so
eazyml_xai_image/Darwin_arm64/eazyml_xai_image/globals/__init__.cpython-311-darwin.so
eazyml_xai_image/Darwin_arm64/eazyml_xai_image/globals/__init__.cpython-312-darwin.so
eazyml_xai_image/Darwin_arm64/eazyml_xai_image/globals/__init__.cpython-38-darwin.so
eazyml_xai_image/Darwin_arm64/eazyml_xai_image/globals/__init__.cpython-39-darwin.so
eazyml_xai_image/Darwin_arm64/eazyml_xai_image/globals/config.cpython-310-darwin.so
eazyml_xai_image/Darwin_arm64/eazyml_xai_image/globals/config.cpython-311-darwin.so
eazyml_xai_image/Darwin_arm64/eazyml_xai_image/globals/config.cpython-312-darwin.so
eazyml_xai_image/Darwin_arm64/eazyml_xai_image/globals/config.cpython-38-darwin.so
eazyml_xai_image/Darwin_arm64/eazyml_xai_image/globals/config.cpython-39-darwin.so
eazyml_xai_image/Darwin_arm64/eazyml_xai_image/globals/global_var.cpython-310-darwin.so
eazyml_xai_image/Darwin_arm64/eazyml_xai_image/globals/global_var.cpython-311-darwin.so
eazyml_xai_image/Darwin_arm64/eazyml_xai_image/globals/global_var.cpython-312-darwin.so
eazyml_xai_image-0.0.46.dist-info/LICENSE
eazyml_xai_image-0.0.46.dist-info/METADATA
eazyml_xai_image-0.0.46.dist-info/WHEEL
eazyml_xai_image-0.0.46.dist-info/top_level.txt
eazyml_xai_image-0.0.46.dist-info/RECORD
